CHANGES.rst
DESCRIPTION.rst
LICENSE
MANIFEST.in
README.md
setup.py
src/seppl/__init__.py
src/seppl/_args.py
src/seppl/_class_registry.py
src/seppl/_entry_points.py
src/seppl/_help.py
src/seppl/_metadata.py
src/seppl/_plugin.py
src/seppl/_registry.py
src/seppl/_session.py
src/seppl/_types.py
src/seppl.egg-info/PKG-INFO
src/seppl.egg-info/SOURCES.txt
src/seppl.egg-info/dependency_links.txt
src/seppl.egg-info/entry_points.txt
src/seppl.egg-info/requires.txt
src/seppl.egg-info/top_level.txt
src/seppl/io/__init__.py
src/seppl/io/_execution.py
src/seppl/io/_filter.py
src/seppl/io/_reader.py
src/seppl/io/_split.py
src/seppl/io/_utils.py
src/seppl/io/_writer.py
src/seppl/placeholders/__init__.py
src/seppl/placeholders/_placeholders.py
src/seppl/tool/__init__.py
src/seppl/tool/escape.py
src/seppl/tool/unescape.py