Metadata-Version: 2.1
Name: seppl
Version: 0.2.21
Summary: Python3 library for parsing pipeline components with their own options.
Home-page: https://github.com/waikato-datamining/seppl
Author: Peter Reutemann
Author-email: fracpete@waikato.ac.nz
License: MIT License
Classifier: Development Status :: 4 - Beta
Classifier: License :: OSI Approved :: MIT License
Classifier: Topic :: Utilities
Classifier: Programming Language :: Python :: 3
License-File: LICENSE
